energy_shaper/__init__.py
energy_shaper/demand_periods.py
energy_shaper/grouper.py
energy_shaper/models.py
energy_shaper/splitter.py
energy_shaper-0.1.1.dist-info/LICENSE.txt
energy_shaper-0.1.1.dist-info/METADATA
energy_shaper-0.1.1.dist-info/RECORD
energy_shaper-0.1.1.dist-info/WHEEL
energy_shaper-0.1.1.dist-info/top_level.txt
